{"data":[{"addr":"上海市延安西路1882号","brief_introduction":"致力于建设“国内一流、国际有影响，有特色的高水平大学”的东华大学以“海纳百川、追求卓越”之勇气，坚持走“观念兴校、学术兴校、管理兴校”发展之路，在“211工程”国家重点建设的高等院校中独树一帜。地理历史：学校地处中国上海，三个校区分别位于松江区和长宁区，占地面积近2000亩，校园环境宜人，系“上海市花园单位”。学校创建于1951年，前身是华东纺织工学院。1985年，更名为中国纺织大学；1999年，更名为东华大学。1960年，被国家教育部确定为全国重点大学，是中国首批具有博士、硕士、学士三级学位授","code":"312000500","college_id":135,"college_nature":"公办","edu_directly":true,"email":"webmaster@dhu.edu.cn","level":"本科","logo":"http://ormuxuvyx.bkt.clouddn.com/college/logo/135.jpg","member_ship":"教育部","name":"东华大学","official_website":null,"old_name":"东华大学 曾用名：中国纺织大学","property":"理工类","province":"上海","ranking":"137","ranking_collegetype":"61","recruit_tel":"021-62379160","recruit_website":"http://www.dhu.edu.cn/","tuition_fee":"1、学费标准（1）一般专业。每人每学年为人民币5000元。（2）艺术类专业。每人每学年为人民币10000元。（3）中外合作办学专业。中德合作的轻化工程专业每人每学年为人民币12000元（国内）；服装与服饰设计专业（中日合作）、服装与服饰设计专业（中英合作）和环境设计（中英合作）每人每学年为人民币30000元（国内）。（4）计算机科学与技术专业、电子信息工程专业和通信工程专业为每人每学年6500元；管理科学与工程类下设的信息管理与信息系统专业为每人每学年6500元，在完成专业大类基础教育后，自主选","type":"普通本科"}],"total":1}